segyio/tools.py
segyio/line.py
segyio/_segyio.cpython-313-i386-linux-gnu.so
segyio/segysampleformat.py
segyio/utils.py
segyio/gather.py
segyio/tracefield.py
segyio/binfield.py
segyio/create.py
segyio/__init__.py
segyio/field.py
segyio/tracesortingformat.py
segyio/segy.py
segyio/open.py
segyio/trace.py
segyio/depth.py
segyio/su/file.py
segyio/su/words.py
segyio/su/__init__.py
segyio-1.9.13.dist-info/RECORD
segyio-1.9.13.dist-info/top_level.txt
segyio-1.9.13.dist-info/METADATA
segyio-1.9.13.dist-info/WHEEL
